{"topicSections":[{"title":"Initializers","identifiers":["doc:\/\/co.pointfree.URLRouting\/documentation\/URLRouting\/PathBuilder\/PathZipVOOOVV\/init(_:_:_:_:_:_:)"]},{"title":"Instance Properties","identifiers":["doc:\/\/co.pointfree.URLRouting\/documentation\/URLRouting\/PathBuilder\/PathZipVOOOVV\/p0","doc:\/\/co.pointfree.URLRouting\/documentation\/URLRouting\/PathBuilder\/PathZipVOOOVV\/p1","doc:\/\/co.pointfree.URLRouting\/documentation\/URLRouting\/PathBuilder\/PathZipVOOOVV\/p2","doc:\/\/co.pointfree.URLRouting\/documentation\/URLRouting\/PathBuilder\/PathZipVOOOVV\/p3","doc:\/\/co.pointfree.URLRouting\/documentation\/URLRouting\/PathBuilder\/PathZipVOOOVV\/p4","doc:\/\/co.pointfree.URLRouting\/documentation\/URLRouting\/PathBuilder\/PathZipVOOOVV\/p5"]},{"title":"Instance Methods","identifiers":["doc:\/\/co.pointfree.URLRouting\/documentation\/URLRouting\/PathBuilder\/PathZipVOOOVV\/parse(_:)"]},{"title":"Default Implementations","generated":true,"identifiers":["doc:\/\/co.pointfree.URLRouting\/documentation\/URLRouting\/PathBuilder\/PathZipVOOOVV\/Parser-Implementations","doc:\/\/co.pointfree.URLRouting\/documentation\/URLRouting\/PathBuilder\/PathZipVOOOVV\/ParserPrinter-Implementations"]}],"hierarchy":{"paths":[["doc:\/\/co.pointfree.URLRouting\/documentation\/URLRouting","doc:\/\/co.pointfree.URLRouting\/documentation\/URLRouting\/PathBuilder"]]},"sections":[],"primaryContentSections":[{"declarations":[{"tokens":[{"text":"struct","kind":"keyword"},{"text":" ","kind":"text"},{"text":"PathZipVOOOVV","kind":"identifier"},{"text":"<","kind":"text"},{"text":"P0","kind":"genericParameter"},{"text":", ","kind":"text"},{"text":"P1","kind":"genericParameter"},{"text":", ","kind":"text"},{"text":"P2","kind":"genericParameter"},{"text":", ","kind":"text"},{"text":"P3","kind":"genericParameter"},{"text":", ","kind":"text"},{"text":"P4","kind":"genericParameter"},{"text":", ","kind":"text"},{"text":"P5","kind":"genericParameter"},{"text":"> ","kind":"text"},{"text":"where","kind":"keyword"},{"text":" ","kind":"text"},{"text":"P0","kind":"typeIdentifier"},{"text":" : ","kind":"text"},{"preciseIdentifier":"s:7Parsing6ParserP","text":"Parser","kind":"typeIdentifier","identifier":"doc:\/\/co.pointfree.URLRouting\/documentation\/Parsing\/Parser"},{"text":", ","kind":"text"},{"text":"P1","kind":"typeIdentifier"},{"text":" : ","kind":"text"},{"preciseIdentifier":"s:7Parsing6ParserP","text":"Parser","kind":"typeIdentifier","identifier":"doc:\/\/co.pointfree.URLRouting\/documentation\/Parsing\/Parser"},{"text":", ","kind":"text"},{"text":"P2","kind":"typeIdentifier"},{"text":" : ","kind":"text"},{"preciseIdentifier":"s:7Parsing6ParserP","text":"Parser","kind":"typeIdentifier","identifier":"doc:\/\/co.pointfree.URLRouting\/documentation\/Parsing\/Parser"},{"text":", ","kind":"text"},{"text":"P3","kind":"typeIdentifier"},{"text":" : ","kind":"text"},{"preciseIdentifier":"s:7Parsing6ParserP","text":"Parser","kind":"typeIdentifier","identifier":"doc:\/\/co.pointfree.URLRouting\/documentation\/Parsing\/Parser"},{"text":", ","kind":"text"},{"text":"P4","kind":"typeIdentifier"},{"text":" : ","kind":"text"},{"preciseIdentifier":"s:7Parsing6ParserP","text":"Parser","kind":"typeIdentifier","identifier":"doc:\/\/co.pointfree.URLRouting\/documentation\/Parsing\/Parser"},{"text":", ","kind":"text"},{"text":"P5","kind":"typeIdentifier"},{"text":" : ","kind":"text"},{"preciseIdentifier":"s:7Parsing6ParserP","text":"Parser","kind":"typeIdentifier","identifier":"doc:\/\/co.pointfree.URLRouting\/documentation\/Parsing\/Parser"},{"text":", ","kind":"text"},{"text":"P0","kind":"typeIdentifier"},{"text":".","kind":"text"},{"text":"Input","kind":"typeIdentifier"},{"text":" == ","kind":"text"},{"preciseIdentifier":"s:Ss","text":"Substring","kind":"typeIdentifier"},{"text":", ","kind":"text"},{"text":"P0","kind":"typeIdentifier"},{"text":".","kind":"text"},{"text":"Output","kind":"typeIdentifier"},{"text":" == ","kind":"text"},{"preciseIdentifier":"s:s4Voida","text":"Void","kind":"typeIdentifier"},{"text":", ","kind":"text"},{"text":"P1","kind":"typeIdentifier"},{"text":".","kind":"text"},{"text":"Input","kind":"typeIdentifier"},{"text":" == ","kind":"text"},{"preciseIdentifier":"s:Ss","text":"Substring","kind":"typeIdentifier"},{"text":", ","kind":"text"},{"text":"P2","kind":"typeIdentifier"},{"text":".","kind":"text"},{"text":"Input","kind":"typeIdentifier"},{"text":" == ","kind":"text"},{"preciseIdentifier":"s:Ss","text":"Substring","kind":"typeIdentifier"},{"text":", ","kind":"text"},{"text":"P3","kind":"typeIdentifier"},{"text":".","kind":"text"},{"text":"Input","kind":"typeIdentifier"},{"text":" == ","kind":"text"},{"preciseIdentifier":"s:Ss","text":"Substring","kind":"typeIdentifier"},{"text":", ","kind":"text"},{"text":"P4","kind":"typeIdentifier"},{"text":".","kind":"text"},{"text":"Input","kind":"typeIdentifier"},{"text":" == ","kind":"text"},{"preciseIdentifier":"s:Ss","text":"Substring","kind":"typeIdentifier"},{"text":", ","kind":"text"},{"text":"P4","kind":"typeIdentifier"},{"text":".","kind":"text"},{"text":"Output","kind":"typeIdentifier"},{"text":" == ","kind":"text"},{"preciseIdentifier":"s:s4Voida","text":"Void","kind":"typeIdentifier"},{"text":", ","kind":"text"},{"text":"P5","kind":"typeIdentifier"},{"text":".","kind":"text"},{"text":"Input","kind":"typeIdentifier"},{"text":" == ","kind":"text"},{"preciseIdentifier":"s:Ss","text":"Substring","kind":"typeIdentifier"},{"text":", ","kind":"text"},{"text":"P5","kind":"typeIdentifier"},{"text":".","kind":"text"},{"text":"Output","kind":"typeIdentifier"},{"text":" == ","kind":"text"},{"preciseIdentifier":"s:s4Voida","text":"Void","kind":"typeIdentifier"}],"platforms":["Linux"],"languages":["swift"]}],"kind":"declarations"}],"variants":[{"paths":["\/documentation\/urlrouting\/pathbuilder\/pathzipvooovv"],"traits":[{"interfaceLanguage":"swift"}]}],"identifier":{"url":"doc:\/\/co.pointfree.URLRouting\/documentation\/URLRouting\/PathBuilder\/PathZipVOOOVV","interfaceLanguage":"swift"},"relationshipsSections":[{"title":"Conforms To","kind":"relationships","type":"conformsTo","identifiers":["doc:\/\/co.pointfree.URLRouting\/documentation\/Parsing\/Parser","doc:\/\/co.pointfree.URLRouting\/documentation\/Parsing\/ParserPrinter"]}],"metadata":{"modules":[{"name":"URLRouting"}],"role":"symbol","title":"PathBuilder.PathZipVOOOVV","extendedModule":"URLRouting","fragments":[{"kind":"keyword","text":"struct"},{"kind":"text","text":" "},{"kind":"identifier","text":"PathZipVOOOVV"}],"navigatorTitle":[{"kind":"identifier","text":"PathZipVOOOVV"}],"symbolKind":"struct","roleHeading":"Structure","externalID":"s:10URLRouting11PathBuilderO0B9ZipVOOOVVV"},"kind":"symbol","schemaVersion":{"minor":3,"patch":0,"major":0},"references":{"doc://co.pointfree.URLRouting/documentation/Parsing/Parser":{"kind":"symbol","role":"symbol","fragments":[{"text":"protocol","kind":"keyword"},{"text":" ","kind":"text"},{"text":"Parser","kind":"identifier"}],"abstract":[{"text":"Declares a type that can incrementally parse an ","type":"text"},{"type":"codeVoice","code":"Output"},{"text":" value from an ","type":"text"},{"type":"codeVoice","code":"Input"},{"text":" value.","type":"text"}],"url":"\/documentation\/parsing\/parser","navigatorTitle":[{"text":"Parser","kind":"identifier"}],"identifier":"doc:\/\/co.pointfree.URLRouting\/documentation\/Parsing\/Parser","title":"Parser","type":"topic"},"doc://co.pointfree.URLRouting/documentation/URLRouting/PathBuilder/PathZipVOOOVV":{"kind":"symbol","fragments":[{"text":"struct","kind":"keyword"},{"text":" ","kind":"text"},{"text":"PathZipVOOOVV","kind":"identifier"}],"role":"symbol","navigatorTitle":[{"text":"PathZipVOOOVV","kind":"identifier"}],"title":"PathBuilder.PathZipVOOOVV","url":"\/documentation\/urlrouting\/pathbuilder\/pathzipvooovv","type":"topic","identifier":"doc:\/\/co.pointfree.URLRouting\/documentation\/URLRouting\/PathBuilder\/PathZipVOOOVV","abstract":[]},"doc://co.pointfree.URLRouting/documentation/URLRouting":{"role":"collection","identifier":"doc:\/\/co.pointfree.URLRouting\/documentation\/URLRouting","title":"URLRouting","type":"topic","url":"\/documentation\/urlrouting","abstract":[{"type":"text","text":"A bidirectional URL router with more type safety and less fuss. This library is built with "},{"isActive":true,"identifier":"http:\/\/github.com\/pointfreeco\/swift-parsing","type":"reference"},{"type":"text","text":"."}],"kind":"symbol"},"doc://co.pointfree.URLRouting/documentation/URLRouting/PathBuilder/PathZipVOOOVV/p3":{"url":"\/documentation\/urlrouting\/pathbuilder\/pathzipvooovv\/p3","role":"symbol","title":"p3","identifier":"doc:\/\/co.pointfree.URLRouting\/documentation\/URLRouting\/PathBuilder\/PathZipVOOOVV\/p3","type":"topic","abstract":[],"kind":"symbol","fragments":[{"kind":"keyword","text":"let"},{"kind":"text","text":" "},{"kind":"identifier","text":"p3"},{"kind":"text","text":": "},{"kind":"typeIdentifier","text":"P3"}]},"doc://co.pointfree.URLRouting/documentation/URLRouting/PathBuilder/PathZipVOOOVV/p1":{"url":"\/documentation\/urlrouting\/pathbuilder\/pathzipvooovv\/p1","role":"symbol","title":"p1","identifier":"doc:\/\/co.pointfree.URLRouting\/documentation\/URLRouting\/PathBuilder\/PathZipVOOOVV\/p1","type":"topic","abstract":[],"kind":"symbol","fragments":[{"kind":"keyword","text":"let"},{"kind":"text","text":" "},{"kind":"identifier","text":"p1"},{"kind":"text","text":": "},{"kind":"typeIdentifier","text":"P1"}]},"doc://co.pointfree.URLRouting/documentation/URLRouting/PathBuilder/PathZipVOOOVV/p0":{"type":"topic","identifier":"doc:\/\/co.pointfree.URLRouting\/documentation\/URLRouting\/PathBuilder\/PathZipVOOOVV\/p0","fragments":[{"text":"let","kind":"keyword"},{"text":" ","kind":"text"},{"text":"p0","kind":"identifier"},{"kind":"text","text":": "},{"kind":"typeIdentifier","text":"P0"}],"url":"\/documentation\/urlrouting\/pathbuilder\/pathzipvooovv\/p0","role":"symbol","abstract":[],"title":"p0","kind":"symbol"},"http://github.com/pointfreeco/swift-parsing":{"url":"http:\/\/github.com\/pointfreeco\/swift-parsing","title":"Parsing","identifier":"http:\/\/github.com\/pointfreeco\/swift-parsing","type":"link","titleInlineContent":[{"type":"text","text":"Parsing"}]},"doc://co.pointfree.URLRouting/documentation/Parsing/ParserPrinter":{"url":"\/documentation\/parsing\/parserprinter","role":"symbol","title":"ParserPrinter","identifier":"doc:\/\/co.pointfree.URLRouting\/documentation\/Parsing\/ParserPrinter","type":"topic","navigatorTitle":[{"kind":"identifier","text":"ParserPrinter"}],"abstract":[{"type":"text","text":"A "},{"isActive":true,"type":"reference","identifier":"doc:\/\/co.pointfree.URLRouting\/documentation\/Parsing\/Parser"},{"type":"text","text":" that can incrementally “print” an output value back into an input."}],"conformance":{"conformancePrefix":[{"text":"Conforms when","type":"text"}],"constraints":[{"code":"P0","type":"codeVoice"},{"text":" conforms to ","type":"text"},{"code":"ParserPrinter","type":"codeVoice"},{"text":", ","type":"text"},{"code":"P1","type":"codeVoice"},{"text":" conforms to ","type":"text"},{"code":"ParserPrinter","type":"codeVoice"},{"text":", ","type":"text"},{"code":"P2","type":"codeVoice"},{"text":" conforms to ","type":"text"},{"code":"ParserPrinter","type":"codeVoice"},{"text":", ","type":"text"},{"code":"P3","type":"codeVoice"},{"text":" conforms to ","type":"text"},{"code":"ParserPrinter","type":"codeVoice"},{"text":", ","type":"text"},{"code":"P4","type":"codeVoice"},{"text":" conforms to ","type":"text"},{"code":"ParserPrinter","type":"codeVoice"},{"text":", ","type":"text"},{"code":"P5","type":"codeVoice"},{"text":" conforms to ","type":"text"},{"code":"ParserPrinter","type":"codeVoice"},{"text":", ","type":"text"},{"code":"P0.Input","type":"codeVoice"},{"text":" is ","type":"text"},{"code":"Substring","type":"codeVoice"},{"text":", ","type":"text"},{"code":"P0.Output","type":"codeVoice"},{"text":" is ","type":"text"},{"code":"Void","type":"codeVoice"},{"text":", ","type":"text"},{"code":"P1.Input","type":"codeVoice"},{"text":" is ","type":"text"},{"code":"Substring","type":"codeVoice"},{"text":", ","type":"text"},{"code":"P2.Input","type":"codeVoice"},{"text":" is ","type":"text"},{"code":"Substring","type":"codeVoice"},{"text":", ","type":"text"},{"code":"P3.Input","type":"codeVoice"},{"text":" is ","type":"text"},{"code":"Substring","type":"codeVoice"},{"text":", ","type":"text"},{"code":"P4.Input","type":"codeVoice"},{"text":" is ","type":"text"},{"code":"Substring","type":"codeVoice"},{"text":", ","type":"text"},{"code":"P4.Output","type":"codeVoice"},{"text":" is ","type":"text"},{"code":"Void","type":"codeVoice"},{"text":", ","type":"text"},{"code":"P5.Input","type":"codeVoice"},{"text":" is ","type":"text"},{"code":"Substring","type":"codeVoice"},{"text":", and ","type":"text"},{"code":"P5.Output","type":"codeVoice"},{"text":" is ","type":"text"},{"code":"Void","type":"codeVoice"},{"text":".","type":"text"}],"availabilityPrefix":[{"type":"text","text":"Available when"}]},"kind":"symbol","fragments":[{"kind":"keyword","text":"protocol"},{"kind":"text","text":" "},{"kind":"identifier","text":"ParserPrinter"}]},"doc://co.pointfree.URLRouting/documentation/URLRouting/PathBuilder/PathZipVOOOVV/p5":{"url":"\/documentation\/urlrouting\/pathbuilder\/pathzipvooovv\/p5","role":"symbol","title":"p5","identifier":"doc:\/\/co.pointfree.URLRouting\/documentation\/URLRouting\/PathBuilder\/PathZipVOOOVV\/p5","type":"topic","abstract":[],"kind":"symbol","fragments":[{"kind":"keyword","text":"let"},{"kind":"text","text":" "},{"kind":"identifier","text":"p5"},{"kind":"text","text":": "},{"kind":"typeIdentifier","text":"P5"}]},"doc://co.pointfree.URLRouting/documentation/URLRouting/PathBuilder/PathZipVOOOVV/p2":{"url":"\/documentation\/urlrouting\/pathbuilder\/pathzipvooovv\/p2","role":"symbol","title":"p2","identifier":"doc:\/\/co.pointfree.URLRouting\/documentation\/URLRouting\/PathBuilder\/PathZipVOOOVV\/p2","type":"topic","abstract":[],"kind":"symbol","fragments":[{"kind":"keyword","text":"let"},{"kind":"text","text":" "},{"kind":"identifier","text":"p2"},{"kind":"text","text":": "},{"kind":"typeIdentifier","text":"P2"}]},"doc://co.pointfree.URLRouting/documentation/URLRouting/PathBuilder/PathZipVOOOVV/Parser-Implementations":{"kind":"article","identifier":"doc:\/\/co.pointfree.URLRouting\/documentation\/URLRouting\/PathBuilder\/PathZipVOOOVV\/Parser-Implementations","abstract":[],"title":"Parser Implementations","url":"\/documentation\/urlrouting\/pathbuilder\/pathzipvooovv\/parser-implementations","role":"collectionGroup","type":"topic"},"doc://co.pointfree.URLRouting/documentation/URLRouting/PathBuilder":{"title":"PathBuilder","role":"symbol","navigatorTitle":[{"kind":"identifier","text":"PathBuilder"}],"url":"\/documentation\/urlrouting\/pathbuilder","kind":"symbol","abstract":[{"type":"text","text":"A custom parameter attribute that constructs path component parsers from closures. The"},{"type":"text","text":" "},{"type":"text","text":"constructed parser runs a number of parsers against each patch component, one after the other,"},{"type":"text","text":" "},{"type":"text","text":"and accumulates their outputs."}],"identifier":"doc:\/\/co.pointfree.URLRouting\/documentation\/URLRouting\/PathBuilder","type":"topic","fragments":[{"kind":"keyword","text":"enum"},{"kind":"text","text":" "},{"kind":"identifier","text":"PathBuilder"}]},"doc://co.pointfree.URLRouting/documentation/URLRouting/PathBuilder/PathZipVOOOVV/parse(_:)":{"url":"\/documentation\/urlrouting\/pathbuilder\/pathzipvooovv\/parse(_:)","role":"symbol","title":"parse(_:)","identifier":"doc:\/\/co.pointfree.URLRouting\/documentation\/URLRouting\/PathBuilder\/PathZipVOOOVV\/parse(_:)","type":"topic","abstract":[{"type":"text","text":"Attempts to parse a nebulous piece of data into something more well-structured. Typically"},{"type":"text","text":" "},{"type":"text","text":"you only call this from other "},{"type":"codeVoice","code":"Parser"},{"type":"text","text":" conformances, not when you want to parse a concrete"},{"type":"text","text":" "},{"type":"text","text":"input."}],"kind":"symbol","fragments":[{"kind":"keyword","text":"func"},{"kind":"text","text":" "},{"kind":"identifier","text":"parse"},{"kind":"text","text":"("},{"kind":"keyword","text":"inout"},{"kind":"text","text":" "},{"preciseIdentifier":"s:10URLRouting14URLRequestDataV","kind":"typeIdentifier","text":"URLRequestData"},{"kind":"text","text":") "},{"kind":"keyword","text":"throws"},{"kind":"text","text":" -> ("},{"kind":"typeIdentifier","text":"P1"},{"kind":"text","text":"."},{"kind":"typeIdentifier","text":"Output"},{"kind":"text","text":", "},{"kind":"typeIdentifier","text":"P2"},{"kind":"text","text":"."},{"kind":"typeIdentifier","text":"Output"},{"kind":"text","text":", "},{"kind":"typeIdentifier","text":"P3"},{"kind":"text","text":"."},{"kind":"typeIdentifier","text":"Output"},{"kind":"text","text":")"}]},"doc://co.pointfree.URLRouting/documentation/URLRouting/PathBuilder/PathZipVOOOVV/p4":{"kind":"symbol","fragments":[{"text":"let","kind":"keyword"},{"text":" ","kind":"text"},{"text":"p4","kind":"identifier"},{"text":": ","kind":"text"},{"text":"P4","kind":"typeIdentifier"}],"role":"symbol","title":"p4","url":"\/documentation\/urlrouting\/pathbuilder\/pathzipvooovv\/p4","type":"topic","identifier":"doc:\/\/co.pointfree.URLRouting\/documentation\/URLRouting\/PathBuilder\/PathZipVOOOVV\/p4","abstract":[]},"doc://co.pointfree.URLRouting/documentation/URLRouting/PathBuilder/PathZipVOOOVV/ParserPrinter-Implementations":{"url":"\/documentation\/urlrouting\/pathbuilder\/pathzipvooovv\/parserprinter-implementations","type":"topic","kind":"article","title":"ParserPrinter Implementations","role":"collectionGroup","identifier":"doc:\/\/co.pointfree.URLRouting\/documentation\/URLRouting\/PathBuilder\/PathZipVOOOVV\/ParserPrinter-Implementations","abstract":[]},"doc://co.pointfree.URLRouting/documentation/URLRouting/PathBuilder/PathZipVOOOVV/init(_:_:_:_:_:_:)":{"kind":"symbol","type":"topic","identifier":"doc:\/\/co.pointfree.URLRouting\/documentation\/URLRouting\/PathBuilder\/PathZipVOOOVV\/init(_:_:_:_:_:_:)","abstract":[],"title":"init(_:_:_:_:_:_:)","role":"symbol","url":"\/documentation\/urlrouting\/pathbuilder\/pathzipvooovv\/init(_:_:_:_:_:_:)","fragments":[{"kind":"identifier","text":"init"},{"kind":"text","text":"("},{"kind":"typeIdentifier","text":"P0"},{"kind":"text","text":", "},{"kind":"typeIdentifier","text":"P1"},{"kind":"text","text":", "},{"kind":"typeIdentifier","text":"P2"},{"kind":"text","text":", "},{"kind":"typeIdentifier","text":"P3"},{"kind":"text","text":", "},{"kind":"typeIdentifier","text":"P4"},{"kind":"text","text":", "},{"kind":"typeIdentifier","text":"P5"},{"kind":"text","text":")"}]}}}